{
  "pages": [ //pages数组中第一项表示应用启动页，参考：https://uniapp.dcloud.io/collocation/pages
    {
      "path": "pages/home/home",
      "style": {
        "navigationBarTitleText": "智慧商城",
        "enablePullDownRefresh": false,
        "navigationBarTextStyle": "white",
        "navigationBarBackgroundColor": "#c21401"
        // "backgroundColor": "#c21401"
      }
    },
    {
      "path": "pages/cart/cart",
      "style": {
        "navigationBarTitleText": "购物车",
        "enablePullDownRefresh": false,
        "navigationBarTextStyle": "black",
        "navigationBarBackgroundColor": "#ffffff"
        // "backgroundColor": "#c21401"
      }
    },
    {
      "path": "pages/cate/cate",
      "style": {
        "navigationBarTitleText": "全部分类",
        "enablePullDownRefresh": false,
        "navigationBarTextStyle": "black",
        "navigationBarBackgroundColor": "#ffffff"
      }
    },
    {
      "path": "pages/my/my",
      "style": {
        "navigationBarTitleText": "111",
        "enablePullDownRefresh": false
      }
    }
  ],
  "globalStyle": {

  },
  "tabBar": {
    "list": [{
        "pagePath": "pages/home/home",
        "iconPath": "static/tabbar/home.png",
        "selectedIconPath": "static/tabbar/home-active.png",
        "text": "首页"
      },
      {
        "pagePath": "pages/cate/cate",
        "iconPath": "static/tabbar/cate.png",
        "selectedIconPath": "static/tabbar/cate-active.png",
        "text": "分类"
      },
      {
        "pagePath": "pages/cart/cart",
        "iconPath": "static/tabbar/cart.png",
        "selectedIconPath": "static/tabbar/cart-active.png",
        "text": "购物车"
      },
      {
        "pagePath": "pages/my/my",
        "iconPath": "static/tabbar/user.png",
        "selectedIconPath": "static/tabbar/user-active.png",
        "text": "我的"
      }
    ]
  },
  "uniIdRouter": {}
}